com2ann.py
com2ann-0.1.1.dist-info/LICENSE
com2ann-0.1.1.dist-info/METADATA
com2ann-0.1.1.dist-info/WHEEL
com2ann-0.1.1.dist-info/entry_points.txt
com2ann-0.1.1.dist-info/top_level.txt
com2ann-0.1.1.dist-info/RECORD
