Metadata-Version: 2.1
Name: com2ann
Version: 0.1.1
Summary: Tool to translate type comments to annotations.
Home-page: https://github.com/ilevkivskyi/com2ann
Author: Ivan Levkivskyi
Author-email: levkivskyi@gmail.com
License: MIT
Keywords: typing function annotations type hints type comments variable annotations
Platform: UNKNOWN
Classifier: Development Status :: 3 - Alpha
Classifier: Environment :: Console
Classifier: Intended Audience :: Developers
Classifier: License :: OSI Approved :: MIT License
Classifier: Operating System :: OS Independent
Classifier: Programming Language :: Python :: 3.8
Classifier: Topic :: Software Development
